[{"company":"kmb","route":"14","routeType":"1","dir":"O","orig":"鯉魚門邨","dest":"中港碼頭","stopList":[{"id":"A41B940A93D63D60","name":"鯉魚門邨巴士總站","lat":"22.294656","long":"114.239386"},{"id":"500EB63FD4A41F66","name":"嘉榮街","lat":"22.293859","long":"114.238561"},{"id":"D024B008AB77435B","name":"油塘巴士總站","lat":"22.295827","long":"114.238484"},{"id":"40FF132FB8E77051","name":"高怡邨","lat":"22.296699","long":"114.241904"},{"id":"B08CA4B3CDCF142A","name":"高俊苑","lat":"22.297943","long":"114.241074"},{"id":"72155034783E2E96","name":"聖安當女書院","lat":"22.301450","long":"114.237648"},{"id":"6C6B36F7550907CE","name":"藍田站","lat":"22.305444","long":"114.234043"},{"id":"47266DB98060A64E","name":"觀塘法院 (F3)","lat":"22.309968","long":"114.229595"},{"id":"FDFA7692A141612F","name":"創紀之城 (B10)","lat":"22.313721","long":"114.222607"},{"id":"5E12682DB792D6DA","name":"觀塘定富街","lat":"22.316300","long":"114.216009"},{"id":"60D0B9706B352D1C","name":"牛頭角下邨","lat":"22.319024","long":"114.214661"},{"id":"D45CEDE6A9DFA30B","name":"德福花園","lat":"22.322178","long":"114.214269"},{"id":"EC757345195E6EAC","name":"九龍灣站","lat":"22.325122","long":"114.213989"},{"id":"427A1FF65094D4D0","name":"啟泰苑","lat":"22.328696","long":"114.211964"},{"id":"B4B94159F6B89A6B","name":"麗晶花園","lat":"22.332434","long":"114.207019"},{"id":"D1AAD1771F3FA9A0","name":"采頤花園","lat":"22.335008","long":"114.202058"},{"id":"C80FB453C9F53569","name":"譽．港灣","lat":"22.332000","long":"114.196917"},{"id":"1C79BF0732EDBD9C","name":"宋皇臺公園","lat":"22.326298","long":"114.189878"},{"id":"225F00F550C301AE","name":"新山道","lat":"22.322068","long":"114.187728"},{"id":"F5795A904B483F33","name":"土瓜灣上鄉道","lat":"22.318431","long":"114.187672"},{"id":"57DFE7792042405B","name":"浙江街遊樂場","lat":"22.314562","long":"114.187656"},{"id":"7CC8FC8889FF1596","name":"新柳街","lat":"22.312282","long":"114.186412"},{"id":"DF4F6B54816F5172","name":"紅磡平治街","lat":"22.309524","long":"114.184594"},{"id":"5CCBD9A6B58BF20D","name":"九龍佑寧堂","lat":"22.305649","long":"114.172574"},{"id":"E049C81469E2B3C0","name":"佐敦白加士街","lat":"22.305172","long":"114.170361"},{"id":"076E1E9D5874C41D","name":"佐敦炮台街","lat":"22.305524","long":"114.168430"},{"id":"D06E5A5B162EF1BA","name":"匯翔道","lat":"22.304716","long":"114.167704"},{"id":"9D843189602DE04F","name":"中港碼頭總站","lat":"22.300005","long":"114.168089"}],"routeId":"14","description":"正常班次"},{"company":"kmb","route":"14","routeType":"1","dir":"I","orig":"中港碼頭","dest":"鯉魚門邨","stopList":[{"id":"9D843189602DE04F","name":"中港碼頭總站","lat":"22.300005","long":"114.168089"},{"id":"450A96AF1DA8E41C","name":"柯士甸站","lat":"22.303707","long":"114.167718"},{"id":"4C49804674904130","name":"佐敦上海街","lat":"22.305631","long":"114.169025"},{"id":"8864CF7D3E4B1EF6","name":"佐敦志和街","lat":"22.305886","long":"114.172499"},{"id":"3CB94742E4B5E3E5","name":"衛理道","lat":"22.306781","long":"114.175981"},{"id":"33033960343A57A8","name":"紅磡山谷道","lat":"22.309321","long":"114.183816"},{"id":"E37FF663075361FE","name":"紅磡北拱街","lat":"22.312219","long":"114.186087"},{"id":"C9051FC04690CD7F","name":"江西街","lat":"22.314723","long":"114.187367"},{"id":"1D093403B1F24DF7","name":"上鄉道","lat":"22.318773","long":"114.187471"},{"id":"9C1D2401E1E06544","name":"新山道","lat":"22.321714","long":"114.187444"},{"id":"47B6BE5FC95C2042","name":"亞皆老街球場","lat":"22.326329","long":"114.189403"},{"id":"EBE826ABDCE44F0C","name":"富豪東方酒店","lat":"22.329172","long":"114.192566"},{"id":"0C063E408709A8D3","name":"景泰街","lat":"22.334190","long":"114.199070"},{"id":"811D4A91C1134CEA","name":"彩虹邨","lat":"22.335336","long":"114.204301"},{"id":"100E6F60BAC1BDEB","name":"坪石邨","lat":"22.333185","long":"114.207227"},{"id":"BA03816A38B9DA7F","name":"啟業邨","lat":"22.330268","long":"114.210894"},{"id":"4BD5CE5106BB0697","name":"九龍灣站","lat":"22.325601","long":"114.214336"},{"id":"6465DE9EE57F6C94","name":"牛頭角下邨","lat":"22.321984","long":"114.214628"},{"id":"3E73B73B12E25DCF","name":"觀塘道休憩處","lat":"22.318039","long":"114.215032"},{"id":"38B86AC474D1060D","name":"創紀之城 (U5)","lat":"22.314442","long":"114.221302"},{"id":"0B8C52E4C34E3B64","name":"觀塘市中心 (T5)","lat":"22.313264","long":"114.224346"},{"id":"144E9479168069DD","name":"觀塘游泳池 (R2)","lat":"22.310432","long":"114.229545"},{"id":"F36C1B3AC57D96FA","name":"藍田站 (落客站)","lat":"22.307670","long":"114.233509"},{"id":"B1B0E08245C0FC15","name":"藍田站","lat":"22.307159","long":"114.233540"},{"id":"C84DC1927320A4AD","name":"聖安當女書院","lat":"22.301268","long":"114.237989"},{"id":"0F9D050D4229C0F7","name":"高俊苑","lat":"22.298050","long":"114.241054"},{"id":"19171A194D7507D5","name":"高怡邨","lat":"22.296682","long":"114.242026"},{"id":"A41B940A93D63D60","name":"鯉魚門邨巴士總站","lat":"22.294656","long":"114.239386"}],"routeId":"14","description":"正常班次"},{"company":"nwfb","route":"14","routeType":null,"dir":"I","orig":"赤柱炮台 (閘口)／馬坑","dest":"嘉亨灣","stopList":[{"id":"002400","name":"赤柱炮台, 黃麻角道","lat":"22.205280632091","long":"114.21435139053"},{"id":"002937","name":"斜炮頂, 黃麻角道","lat":"22.206058122091","long":"114.21397032053"},{"id":"002579","name":"富豪海灣, 黃麻角道","lat":"22.207667162091","long":"114.21351468053"},{"id":"002385","name":"聖士提反書院附屬小學, 黃麻角道","lat":"22.212419072091","long":"114.21665931053"},{"id":"002360","name":"鄧肇堅運動場, 黃麻角道","lat":"22.216834092091","long":"114.21384755053"},{"id":"002303","name":"香港航海學校, 東頭灣道","lat":"22.218215302091","long":"114.21414073053"},{"id":"002304","name":"聖士提反書院, 東頭灣道","lat":"22.216554552091","long":"114.21725399053"},{"id":"002305","name":"赤柱監獄, 東頭灣道","lat":"22.215506742091","long":"114.21766010053"},{"id":"002302","name":"聖士提反書院, 東頭灣道","lat":"22.216536362091","long":"114.21719449053"},{"id":"002275","name":"赤柱警署, 赤柱村道","lat":"22.218519742091","long":"114.21301176053"},{"id":"002378","name":"赤柱廣場","lat":"22.220223252091","long":"114.20920230053"},{"id":"002387","name":"馬坑邨駿馬樓, 環角道","lat":"22.222205242091","long":"114.20584898053"},{"id":"002175","name":"馬坑邨觀馬樓, 環角道","lat":"22.220581052091","long":"114.20669370053"},{"id":"002278","name":"赤柱崗道, 赤柱村道","lat":"22.221785752091","long":"114.21114294053"},{"id":"002279","name":"赤柱灘道, 赤柱村道","lat":"22.224033782091","long":"114.21335388053"},{"id":"002282","name":"輝百苑, 大潭道","lat":"22.225645112091","long":"114.21572025053"},{"id":"002283","name":"曼克頓花園, 大潭道","lat":"22.228602102091","long":"114.21770422053"},{"id":"002286","name":"龜背灣, 大潭道","lat":"22.235610432091","long":"114.22277786053"},{"id":"002287","name":"大潭郊野公園, 大潭道","lat":"22.240152462091","long":"114.22134076053"},{"id":"002288","name":"大潭水塘 (南), 大潭道","lat":"22.242812552091","long":"114.22192341053"},{"id":"002293","name":"大潭水塘 (北), 大潭道","lat":"22.246545802091","long":"114.22117045053"},{"id":"002289","name":"石澳道, 大潭道","lat":"22.256907952091","long":"114.22807111053"},{"id":"001321","name":"女童軍訓練中心, 大潭道","lat":"22.263971382091","long":"114.23059713053"},{"id":"001322","name":"山翠苑, 大潭道","lat":"22.269012232091","long":"114.23272045053"},{"id":"001232","name":"筲箕灣東官立中學, 柴灣道","lat":"22.272471812091","long":"114.23263770053"},{"id":"001233","name":"阿公岩道, 柴灣道","lat":"22.274719782091","long":"114.23085406053"},{"id":"001300","name":"南安里, 筲箕灣道","lat":"22.277420312091","long":"114.22717089053"},{"id":"001301","name":"新成街, 筲箕灣道","lat":"22.278724872091","long":"114.22622512053"},{"id":"001302","name":"海晏街, 筲箕灣道","lat":"22.280716692091","long":"114.22345551053"},{"id":"001303","name":"西灣河文娛中心, 筲箕灣道","lat":"22.281794772091","long":"114.22202073053"},{"id":"001313","name":"太康樓, 太康街","lat":"22.283340892091","long":"114.22177946053"},{"id":"003155","name":"西灣河 (嘉亨灣)","lat":"22.284739002091","long":"114.22425488053"}],"routeId":"14","description":"正常班次"},{"company":"nwfb","route":"14","routeType":null,"dir":"O","orig":"嘉亨灣","dest":"赤柱炮台 (閘口)／馬坑","stopList":[{"id":"003155","name":"西灣河 (嘉亨灣)","lat":"22.284739002091","long":"114.22425488053"},{"id":"001316","name":"西灣河站, 太安街","lat":"22.282354632091","long":"114.22239868053"},{"id":"001297","name":"海晏街, 筲箕灣道","lat":"22.280776032091","long":"114.22363882053"},{"id":"001298","name":"愛秩序灣道, 筲箕灣道","lat":"22.280349712091","long":"114.22504094053"},{"id":"001299","name":"南安里, 筲箕灣道","lat":"22.277849882091","long":"114.22690650053"},{"id":"002770","name":"明華大廈, 柴灣道","lat":"22.275813922091","long":"114.23037523053"},{"id":"001216","name":"阿公岩道, 柴灣道","lat":"22.274447992091","long":"114.23121621053"},{"id":"001217","name":"鯉魚門公園, 柴灣道","lat":"22.273682822091","long":"114.23182613053"},{"id":"001317","name":"山翠苑, 大潭道","lat":"22.269405042091","long":"114.23309456053"},{"id":"001318","name":"女童軍訓練中心, 大潭道","lat":"22.263569562091","long":"114.23041293053"},{"id":"001319","name":"新橋面, 大潭道","lat":"22.263060292091","long":"114.22549684053"},{"id":"001320","name":"西灣濾水廠, 大潭道","lat":"22.257696712091","long":"114.22792689053"},{"id":"002291","name":"大潭水塘 (北), 大潭道","lat":"22.246104312091","long":"114.22121771053"},{"id":"002290","name":"大潭郊野公園, 大潭道","lat":"22.239590912091","long":"114.22141999053"},{"id":"002292","name":"龜背灣, 大潭道","lat":"22.235417572091","long":"114.22298762053"},{"id":"002285","name":"美國會所, 大潭道","lat":"22.227604522091","long":"114.21744399053"},{"id":"002284","name":"聽濤小築, 大潭道","lat":"22.225601502091","long":"114.21584308053"},{"id":"002280","name":"旭逸居, 赤柱村道","lat":"22.223961602091","long":"114.21338878053"},{"id":"002276","name":"海灣園, 赤柱村道","lat":"22.221121932091","long":"114.21170439053"},{"id":"002281","name":"赤柱村, 赤柱村道","lat":"22.219069792091","long":"114.21291885053"},{"id":"002303","name":"香港航海學校, 東頭灣道","lat":"22.218215302091","long":"114.21414073053"},{"id":"002304","name":"聖士提反書院, 東頭灣道","lat":"22.216554552091","long":"114.21725399053"},{"id":"002305","name":"赤柱監獄, 東頭灣道","lat":"22.215506742091","long":"114.21766010053"},{"id":"002302","name":"聖士提反書院, 東頭灣道","lat":"22.216536362091","long":"114.21719449053"},{"id":"002359","name":"黃麻角道公立醫局, 黃麻角道","lat":"22.218017182091","long":"114.21352325053"},{"id":"002362","name":"聖士提反書院附屬小學, 黃麻角道","lat":"22.212433142091","long":"114.21669723053"},{"id":"002578","name":"富豪海灣, 黃麻角道","lat":"22.207885932091","long":"114.21354160053"},{"id":"002400","name":"赤柱炮台, 黃麻角道","lat":"22.205280632091","long":"114.21435139053"},{"id":"002937","name":"斜炮頂, 黃麻角道","lat":"22.206058122091","long":"114.21397032053"},{"id":"002579","name":"富豪海灣, 黃麻角道","lat":"22.207667162091","long":"114.21351468053"},{"id":"002385","name":"聖士提反書院附屬小學, 黃麻角道","lat":"22.212419072091","long":"114.21665931053"},{"id":"002360","name":"鄧肇堅運動場, 黃麻角道","lat":"22.216834092091","long":"114.21384755053"},{"id":"002304","name":"聖士提反書院, 東頭灣道","lat":"22.216554552091","long":"114.21725399053"},{"id":"002305","name":"赤柱監獄, 東頭灣道","lat":"22.215506742091","long":"114.21766010053"},{"id":"002302","name":"聖士提反書院, 東頭灣道","lat":"22.216536362091","long":"114.21719449053"},{"id":"002275","name":"赤柱警署, 赤柱村道","lat":"22.218519742091","long":"114.21301176053"},{"id":"002378","name":"赤柱廣場","lat":"22.220223252091","long":"114.20920230053"}],"routeId":"14","description":"正常班次"}]