[{"company":"kmb","route":"213B","routeType":"1","dir":"O","orig":"安泰","dest":"觀塘(循環線)","stopList":[{"id":"716E5DBD24DCE28B","name":"安泰總站","lat":"22.326944","long":"114.230431"},{"id":"51657C54B75A5304","name":"愛達樓","lat":"22.323350","long":"114.231662"},{"id":"B930999AA5F7E997","name":"安達邨","lat":"22.320067","long":"114.234642"},{"id":"B5CB3F0D26BBBD03","name":"觀塘同仁街","lat":"22.313363","long":"114.226412"},{"id":"AA52228890817D12","name":"善達樓","lat":"22.320283","long":"114.235550"},{"id":"389B25932AD10BA3","name":"愛達樓","lat":"22.321842","long":"114.232593"},{"id":"716E5DBD24DCE28B","name":"安泰總站","lat":"22.326944","long":"114.230431"}],"routeId":"213B"}]