[{"company":"kmb","route":"54","routeType":"1","dir":"O","orig":"元朗(西)","dest":"上村(循環線)","stopList":[{"id":"FAB0AB2B6DCEE7F2","name":"元朗（西）總站","lat":"22.445364","long":"114.024859"},{"id":"C296D9B3313C1F77","name":"元朗同樂街 (N9)","lat":"22.444617","long":"114.028259"},{"id":"445B2A02DB891CA9","name":"元朗谷亭街 (N14)","lat":"22.444580","long":"114.030435"},{"id":"0C943B7308FF4DCC","name":"形點 II","lat":"22.446616","long":"114.035376"},{"id":"73CDC61EBA1C9431","name":"形點 I","lat":"22.445065","long":"114.036445"},{"id":"D9AB3B959A46E411","name":"博愛醫院","lat":"22.445005","long":"114.040216"},{"id":"36DC37F6A54BA5E0","name":"東成里","lat":"22.444407","long":"114.043751"},{"id":"F5FA7ED5D5A6860D","name":"凹頭","lat":"22.444159","long":"114.048568"},{"id":"D05C7D74301D47C5","name":"下高埔村","lat":"22.442496","long":"114.051608"},{"id":"41C9D989B8B874FF","name":"高埔村","lat":"22.440430","long":"114.056288"},{"id":"E67CDE5E499A9529","name":"蒙養小學","lat":"22.440022","long":"114.061520"},{"id":"DA9E78C0D00A5C00","name":"泰康圍","lat":"22.440141","long":"114.063293"},{"id":"754018D85575639C","name":"錦田郵局","lat":"22.439985","long":"114.066296"},{"id":"EFF76047DAB0578D","name":"大江埔","lat":"22.439808","long":"114.068318"},{"id":"847F5319F0265428","name":"吳家村","lat":"22.437719","long":"114.069297"},{"id":"6D76943277DC18FF","name":"沙田坑村","lat":"22.435974","long":"114.067605"},{"id":"1E81121E54BA1E71","name":"錦上路站","lat":"22.434510","long":"114.064924"},{"id":"13211112A23954EC","name":"沙田坑","lat":"22.435917","long":"114.067226"},{"id":"3A317C6B1C25E38B","name":"吳家村","lat":"22.437507","long":"114.068769"},{"id":"D718ABC314AD4B3C","name":"彭家村","lat":"22.440264","long":"114.074592"},{"id":"B930AD84BC1A8655","name":"八鄉石崗橋","lat":"22.440537","long":"114.077602"},{"id":"F3BA995562185F8D","name":"七星崗","lat":"22.441527","long":"114.082918"},{"id":"D790D851F74E29ED","name":"石崗菜站","lat":"22.441570","long":"114.085662"},{"id":"FF3C034E01D2F73B","name":"八鄉消防局","lat":"22.440951","long":"114.089993"},{"id":"F3C6FD22BC86B80F","name":"羅屋村","lat":"22.439245","long":"114.093510"},{"id":"784D9D1F3FFC2A71","name":"芝麻嶺","lat":"22.437950","long":"114.097991"},{"id":"8581AEE08587F6AE","name":"磚窰","lat":"22.434458","long":"114.101749"},{"id":"9E082924A8362902","name":"上村總站","lat":"22.432078","long":"114.103338"},{"id":"0E7D925FC7469830","name":"八鄉古廟","lat":"22.432645","long":"114.102618"},{"id":"22D8393C78C95BBC","name":"磚窰","lat":"22.434615","long":"114.101651"},{"id":"13362EE5DC44432F","name":"芝麻嶺","lat":"22.437643","long":"114.097938"},{"id":"11387D20F8DCA372","name":"羅屋村","lat":"22.439335","long":"114.093261"},{"id":"F853FAA669228E41","name":"八鄉警署","lat":"22.440998","long":"114.089028"},{"id":"6B35AF30748EDA1B","name":"石崗菜站","lat":"22.441636","long":"114.086366"},{"id":"2D10E16919B5A96E","name":"八鄉石崗橋","lat":"22.440583","long":"114.079044"},{"id":"F0D6CB5F04988EA4","name":"錦田診所","lat":"22.440051","long":"114.074343"},{"id":"09601DB251157030","name":"吳家村","lat":"22.437825","long":"114.069419"},{"id":"B683B48A5CCC6C2B","name":"沙田坑村","lat":"22.436280","long":"114.067890"},{"id":"4EBE182141C52094","name":"錦上路站","lat":"22.434342","long":"114.064494"},{"id":"EA74F13EEC20AD91","name":"沙田坑","lat":"22.435852","long":"114.067119"},{"id":"9229BF150F3C53BC","name":"吳家村","lat":"22.437194","long":"114.068529"},{"id":"3291342581C48037","name":"大江埔","lat":"22.439722","long":"114.069489"},{"id":"D1C1E33BB9350C65","name":"錦田","lat":"22.439602","long":"114.066792"},{"id":"F6FDEAF741BFBD2E","name":"錦田街市","lat":"22.439869","long":"114.065372"},{"id":"1345D70225C59BD3","name":"吉慶圍","lat":"22.440040","long":"114.062414"},{"id":"3210F3BCFFD74E61","name":"蒙養小學","lat":"22.439838","long":"114.061013"},{"id":"BFCFEBF6F5C35402","name":"高埔村","lat":"22.440176","long":"114.056258"},{"id":"F8B3A5C8D0D3CED7","name":"下高埔村","lat":"22.441913","long":"114.052704"},{"id":"3D5F826FD00C0529","name":"凹頭","lat":"22.443185","long":"114.050075"},{"id":"876CF2E8C375F78B","name":"東成里","lat":"22.443935","long":"114.045892"},{"id":"6386333EDAC64C96","name":"楊屋村","lat":"22.444260","long":"114.042387"},{"id":"0FD6C16477F1F0E8","name":"博愛醫院","lat":"22.445093","long":"114.040096"},{"id":"6A4B371546D489BF","name":"形點 I","lat":"22.444324","long":"114.035984"},{"id":"AC935792C88AF135","name":"元朗又新街 (S5)","lat":"22.444300","long":"114.030811"},{"id":"43E5D3A445382F82","name":"元朗大棠路 (S8)","lat":"22.444344","long":"114.028219"},{"id":"FAB0AB2B6DCEE7F2","name":"元朗（西）總站","lat":"22.445364","long":"114.024859"}],"routeId":"54"}]