[{"company":"kmb","route":"272X","routeType":"1","dir":"O","orig":"大埔中心","dest":"旺角東站","stopList":[{"id":"8259A9EF4DB191A6","name":"大埔中心總站 (TP905)","lat":"22.453151","long":"114.169308"},{"id":"45628FA7B8D7C5D2","name":"大埔安祥路 (TP537)","lat":"22.451613","long":"114.167462"},{"id":"F7DD5A5E7E4D41C9","name":"廣福道轉車站 (TP567)","lat":"22.448149","long":"114.168134"},{"id":"3FD481FB9B9DC36C","name":"大埔運頭角里 (TP569)","lat":"22.447394","long":"114.169932"},{"id":"062FFE8F1560E8A4","name":"廣福邨 (TP575)","lat":"22.446623","long":"114.173374"},{"id":"74648B92E0E80E2E","name":"白石角變電站 (PA201)","lat":"22.434893","long":"114.201372"},{"id":"261392BB77CC768D","name":"天賦海灣 (PA203)","lat":"22.431492","long":"114.201558"},{"id":"33ABA49F0E91A247","name":"雲滙 (PA209)","lat":"22.429805","long":"114.203323"},{"id":"023E9E5A9E073E1A","name":"創新路 (PA211)","lat":"22.428649","long":"114.204981"},{"id":"B644204AEDE7A031","name":"科研路 (PA215)","lat":"22.426442","long":"114.208450"},{"id":"5C2A974134634635","name":"科學園(第一期) (PA220)","lat":"22.424272","long":"114.211589"},{"id":"A0D379E172F5BC93","name":"香港生物科技研究院 (PA232)","lat":"22.422664","long":"114.214179"},{"id":"853CD1316EB5227B","name":"水上活動中心 (PA236)","lat":"22.418662","long":"114.214271"},{"id":"BE6EC9708F5FB613","name":"馬料水公眾碼頭 (PA238)","lat":"22.416027","long":"114.213945"},{"id":"480DB16994F8FFEE","name":"青沙公路轉車站 (TA750)","lat":"22.358632","long":"114.163389"},{"id":"673B33867260EBB7","name":"青沙公路轉車站 (A4) (TA752)","lat":"22.358523","long":"114.163314"},{"id":"5A0D9C9441ED6AC5","name":"大角咀中匯街 (MK296)","lat":"22.322767","long":"114.159836"},{"id":"9BF9C994F2DAE15D","name":"奧運站 (MK297)","lat":"22.318545","long":"114.160606"},{"id":"B76B249D3D253008","name":"富貴街 (MK200)","lat":"22.318679","long":"114.161867"},{"id":"3F34A16B40CB1C7F","name":"銘基書院 (MK132)","lat":"22.318844","long":"114.164162"},{"id":"14DDE929D10FE4B7","name":"新填地街 (MK322)","lat":"22.319532","long":"114.167481"},{"id":"4459E386C8525C34","name":"旺角道 花園街街市 (MK336)","lat":"22.321187","long":"114.170468"},{"id":"DB22EE221876DD43","name":"旺角東站 MOKO (MK905)","lat":"22.322613","long":"114.172230"}],"routeId":"272X","description":"正常班次"},{"company":"kmb","route":"272X","routeType":"1","dir":"I","orig":"旺角東站","dest":"大埔中心","stopList":[{"id":"DB22EE221876DD43","name":"旺角東站 MOKO (MK905)","lat":"22.322613","long":"114.172230"},{"id":"F7CAA2D4FF9D61F7","name":"太子站, 旺角花墟 (MK751)","lat":"22.324126","long":"114.169855"},{"id":"DE27CD3EB0AF43D8","name":"旺角道 花園街街市 (MK333)","lat":"22.321077","long":"114.169853"},{"id":"9B1BE296C2AC5F97","name":"旺角站 (MK624)","lat":"22.319384","long":"114.170415"},{"id":"7ADC6D521E6BECE6","name":"旺角街市, 地區康健中心 (MK626)","lat":"22.318792","long":"114.167024"},{"id":"E02E10C9135624F9","name":"銘基書院 (MK632)","lat":"22.318599","long":"114.164385"},{"id":"3B8B261C1DA409BD","name":"帝柏海灣 奧海城 (MK633)","lat":"22.317868","long":"114.162187"},{"id":"9DA7325E4238402B","name":"奧運站 (MK656)","lat":"22.318378","long":"114.160423"},{"id":"195C509959C6A799","name":"君匯港 (MK657)","lat":"22.322229","long":"114.159642"},{"id":"2F202818B5A6F424","name":"青沙公路轉車站 (B1) (TA296)","lat":"22.360835","long":"114.163009"},{"id":"739A5DDE0CF1970C","name":"馬料水公眾碼頭 (PA100)","lat":"22.415908","long":"114.213778"},{"id":"9E95343C77BB85E2","name":"水上活動中心 (PA104)","lat":"22.420023","long":"114.214250"},{"id":"2D1A8946EF054FC9","name":"香港生物科技研究院 (PA107)","lat":"22.423223","long":"114.213922"},{"id":"DADEC4FDAD7C58B3","name":"科學園(第一期) (PA122)","lat":"22.424247","long":"114.211432"},{"id":"E8F5E085BAEFE100","name":"科研路 (PA124)","lat":"22.426628","long":"114.208027"},{"id":"79FD1B44D37205B8","name":"雲滙 (PA127)","lat":"22.429561","long":"114.203338"},{"id":"369A5601F8A63B5E","name":"白石角 (PA129)","lat":"22.431492","long":"114.201512"},{"id":"A339426A8F633D63","name":"白石角變電站 (PA130)","lat":"22.433895","long":"114.200812"},{"id":"CDB292D507E4302D","name":"廣福邨　 (TP267)","lat":"22.446299","long":"114.173076"},{"id":"4EF065C6D7FCCFE7","name":"廣福道轉車站 (TP278)","lat":"22.448116","long":"114.167887"},{"id":"2AEDE966C122B71E","name":"廣福道轉車站 - 寶鄉橋 (TP304)","lat":"22.449850","long":"114.166991"},{"id":"6716018C3EE42733","name":"大埔安祥路 (TP311)","lat":"22.451779","long":"114.167238"},{"id":"8259A9EF4DB191A6","name":"大埔中心總站 (TP905)","lat":"22.453151","long":"114.169308"}],"routeId":"272X","description":"正常班次"}]