[{"company":"kmb","route":"46R","routeType":"1","dir":"O","orig":"大圍站","dest":"昂船洲軍營","stopList":[{"id":"14C3BF43DC0878D1","name":"大圍站總站 (G2) (TA941)","lat":"22.373074","long":"114.180370"},{"id":"673B33867260EBB7","name":"青沙公路轉車站 (A4) (TA752)","lat":"22.358523","long":"114.163314"},{"id":"9E76DA1634822CDB","name":"昂船洲軍營 (SS350)","lat":"22.318818","long":"114.131223"}],"routeId":"46R","description":"正常班次"},{"company":"kmb","route":"46R","routeType":"1","dir":"I","orig":"昂船洲軍營","dest":"大圍站","stopList":[{"id":"9E76DA1634822CDB","name":"昂船洲軍營 (SS350)","lat":"22.318818","long":"114.131223"},{"id":"BF72FF473A660C0E","name":"青沙公路轉車站 (B4) (TA293)","lat":"22.360534","long":"114.162877"},{"id":"14C3BF43DC0878D1","name":"大圍站總站 (G2) (TA941)","lat":"22.373074","long":"114.180370"}],"routeId":"46R","description":"正常班次"}]