[{"company":"ctb","route":"47P","routeType":null,"dir":"O","orig":"堅尼地城 (卑路乍灣)","dest":"黃竹坑","stopList":[{"id":"001177","name":"卑路乍灣","lat":"22.284612","long":"114.128454"},{"id":"001183","name":"西祥街","lat":"22.285066","long":"114.131681"},{"id":"001003","name":"山市街, 卑路乍街","lat":"22.283632","long":"114.130634"},{"id":"001004","name":"北街, 卑路乍街","lat":"22.282647","long":"114.128668"},{"id":"001005","name":"聯邦新樓, 卑路乍街","lat":"22.282463","long":"114.127608"},{"id":"001164","name":"加惠民道, 域多利道","lat":"22.282073","long":"114.124935"},{"id":"001165","name":"西寧閣, 域多利道","lat":"22.281064","long":"114.120807"},{"id":"001166","name":"港島西廢物轉運站, 域多利道","lat":"22.280253","long":"114.118682"},{"id":"001167","name":"明愛賽馬會宿舍, 域多利道","lat":"22.278604","long":"114.117789"},{"id":"001168","name":"摩星嶺徑, 域多利道","lat":"22.275761","long":"114.117524"},{"id":"002384","name":"摩星嶺道, 域多利道","lat":"22.274018","long":"114.118537"},{"id":"002307","name":"趙苑, 域多利道","lat":"22.272910","long":"114.120207"},{"id":"002308","name":"碧海閣, 域多利道","lat":"22.272585","long":"114.124393"},{"id":"002309","name":"西島中學, 域多利道","lat":"22.273205","long":"114.126274"},{"id":"002310","name":"香港華人基督教聯會薄扶林道墳場, 域多利道","lat":"22.272366","long":"114.127777"},{"id":"002327","name":"美景臺, 域多利道","lat":"22.270093","long":"114.125527"},{"id":"002311","name":"碧荔道, 域多利道","lat":"22.268918","long":"114.126386"},{"id":"002312","name":"沙宣道, 域多利道","lat":"22.266569","long":"114.127951"},{"id":"002313","name":"香港大學李嘉誠醫學院, 域多利道","lat":"22.267142","long":"114.129452"},{"id":"002314","name":"下碧瑤灣, 域多利道","lat":"22.263660","long":"114.132249"},{"id":"002315","name":"上碧瑤灣, 域多利道","lat":"22.261643","long":"114.133740"},{"id":"002680","name":"華翠街, 域多利道","lat":"22.255139","long":"114.136077"},{"id":"002260","name":"華富道, 石排灣道","lat":"22.252239","long":"114.140805"},{"id":"003287","name":"興和街, 石排灣道","lat":"22.249678","long":"114.147902"},{"id":"002157","name":"聖伯多祿堂, 香港仔大道","lat":"22.249804","long":"114.153680"},{"id":"002158","name":"漁暉道, 香港仔大道","lat":"22.248586","long":"114.155755"},{"id":"002159","name":"業漁大廈, 香港仔大道","lat":"22.247579","long":"114.158491"},{"id":"002344","name":"甄沾記大廈, 黃竹坑道","lat":"22.248523","long":"114.163625"},{"id":"002383","name":"業興街, 黃竹坑道","lat":"22.249541","long":"114.168112"},{"id":"002399","name":"香港醫學專科學院, 海洋公園道","lat":"22.251178","long":"114.170620"},{"id":"002371","name":"港鐵黃竹坑車廠, 警校道","lat":"22.246167","long":"114.169099"}],"routeId":"47P","description":"正常班次"}]