[{"company":"gmb","route":"803","routeType":1,"orig":"顯徑","dest":"利安","stopList":[{"id":20002241,"name":"顯田街, 近梁文燕紀念中學","lat":"22.361762","long":"114.174321"},{"id":20002242,"name":"顯徑街, 顯徑邨顯慶樓外","lat":"22.363677","long":"114.173583"},{"id":20002243,"name":"顯徑街, 田心救護站外","lat":"22.366124","long":"114.175903"},{"id":20001580,"name":"田心街, 隆亨邨榮心樓對面","lat":"22.369131","long":"114.179399"},{"id":20001582,"name":"車公廟路, 五育中學對面","lat":"22.372482","long":"114.180166"},{"id":20002244,"name":"車公廟路, 李屋村對面","lat":"22.374658","long":"114.184225"},{"id":20001581,"name":"車公廟路, 車公廟站外","lat":"22.374522","long":"114.186506"},{"id":20002245,"name":"大涌橋路, 曾大屋遊樂場對面","lat":"22.375768","long":"114.189041"},{"id":20002246,"name":"大涌橋路, 愉城苑對面","lat":"22.378143","long":"114.191488"},{"id":20001556,"name":"大涌橋路, 近河畔花園","lat":"22.382234","long":"114.195392"},{"id":20001557,"name":"大涌橋路, 富豪花園對面","lat":"22.385078","long":"114.198131"},{"id":20002235,"name":"大涌橋路, 沙田第一城對面","lat":"22.389394","long":"114.203094"},{"id":20001567,"name":"大涌橋路, 濱景花園外","lat":"22.391768","long":"114.206328"},{"id":20002236,"name":"亞公角街北行線, 沙田醫院對面","lat":"22.399660","long":"114.212826"},{"id":20002238,"name":"亞公角街, 近富安花園","lat":"22.406132","long":"114.221889"},{"id":20019633,"name":"馬鞍山路錦駿苑對面 ","lat":"22.411609","long":"114.224247"},{"id":20001226,"name":"恒康街, 耀安邨耀謙樓對面","lat":"22.417960","long":"114.230489"},{"id":20001228,"name":"恒康街, 曾璧山中學對面","lat":"22.421744","long":"114.228587"},{"id":20001230,"name":"西沙路, 馬鞍山廣場外","lat":"22.425021","long":"114.231502"},{"id":20002247,"name":"馬鞍山路, 馬鞍山分區警署外","lat":"22.422483","long":"114.233016"},{"id":20002287,"name":"錦英路, 富寶花園外","lat":"22.423917","long":"114.238553"},{"id":20002248,"name":"利安邨巴士總站","lat":"22.425361","long":"114.240953"}],"routeId":2010269,"description":"正常班次"},{"company":"gmb","route":"803","routeType":2,"orig":"利安","dest":"顯徑","stopList":[{"id":20002248,"name":"利安邨巴士總站","lat":"22.425361","long":"114.240953"},{"id":20002249,"name":"錦英路, 錦龍苑對面","lat":"22.425921","long":"114.239516"},{"id":20002250,"name":"西沙路南行線, 雅典居對面","lat":"22.425516","long":"114.235591"},{"id":20001234,"name":"西沙路, 新港城外","lat":"22.424551","long":"114.231764"},{"id":20001236,"name":"恒康街, 曾璧山中學外","lat":"22.421906","long":"114.228800"},{"id":20001238,"name":"恒康街, 耀安邨耀平樓外","lat":"22.418348","long":"114.230188"},{"id":20019666,"name":"馬鞍山路近錦駿苑 ","lat":"22.413379","long":"114.226940"},{"id":20002226,"name":"恆德街南行線, 近大水坑站","lat":"22.407405","long":"114.222948"},{"id":20002228,"name":"亞公角街, 沙田醫院外","lat":"22.398751","long":"114.212293"},{"id":20001563,"name":"大涌橋路, 濱景花園對面","lat":"22.391642","long":"114.206580"},{"id":20001564,"name":"大涌橋路, 沙田第一城外","lat":"22.388884","long":"114.202554"},{"id":20001553,"name":"大涌橋路, 富豪花園外","lat":"22.384979","long":"114.198441"},{"id":20001554,"name":"大涌橋路,近河畔花園","lat":"22.381818","long":"114.195372"},{"id":20002251,"name":"大涌橋路, 乙明村外","lat":"22.377475","long":"114.191177"},{"id":20002252,"name":"大涌橋路, 曾大屋遊樂場外","lat":"22.375714","long":"114.189439"},{"id":20001571,"name":"車公廟路, 秦石邨外巴士站","lat":"22.374396","long":"114.187264"},{"id":20002253,"name":"車公廟路, 李屋村外","lat":"22.374360","long":"114.184215"},{"id":20001572,"name":"車公廟路, 五育中學外","lat":"22.372247","long":"114.180350"},{"id":20002254,"name":"車公廟路, 田心外","lat":"22.370694","long":"114.177933"},{"id":20002241,"name":"顯田街, 近梁文燕紀念中學","lat":"22.361762","long":"114.174321"}],"routeId":2010269,"description":"正常班次"},{"company":"gmb","route":"803","routeType":1,"orig":"顯徑","dest":"利安","stopList":[{"id":20002241,"name":"顯田街, 近梁文燕紀念中學","lat":"22.361762","long":"114.174321"},{"id":20002242,"name":"顯徑街, 顯徑邨顯慶樓外","lat":"22.363677","long":"114.173583"},{"id":20002243,"name":"顯徑街, 田心救護站外","lat":"22.366124","long":"114.175903"},{"id":20001582,"name":"車公廟路, 五育中學對面","lat":"22.372482","long":"114.180166"},{"id":20002244,"name":"車公廟路, 李屋村對面","lat":"22.374658","long":"114.184225"},{"id":20001581,"name":"車公廟路, 車公廟站外","lat":"22.374522","long":"114.186506"},{"id":20002245,"name":"大涌橋路, 曾大屋遊樂場對面","lat":"22.375768","long":"114.189041"},{"id":20002246,"name":"大涌橋路, 愉城苑對面","lat":"22.378143","long":"114.191488"},{"id":20001556,"name":"大涌橋路, 近河畔花園","lat":"22.382234","long":"114.195392"},{"id":20001557,"name":"大涌橋路, 富豪花園對面","lat":"22.385078","long":"114.198131"},{"id":20002235,"name":"大涌橋路, 沙田第一城對面","lat":"22.389394","long":"114.203094"},{"id":20001567,"name":"大涌橋路, 濱景花園外","lat":"22.391768","long":"114.206328"},{"id":20019633,"name":"馬鞍山路, 錦駿苑對面 ","lat":"22.411609","long":"114.224247"},{"id":20001226,"name":"恒康街, 耀安邨耀謙樓對面","lat":"22.417960","long":"114.230489"},{"id":20001228,"name":"恒康街, 曾璧山中學對面","lat":"22.421744","long":"114.228587"},{"id":20001230,"name":"西沙路, 馬鞍山廣場外","lat":"22.425021","long":"114.231502"},{"id":20002247,"name":"馬鞍山路, 馬鞍山分區警署外","lat":"22.422483","long":"114.233016"},{"id":20002287,"name":"錦英路, 富寶花園外","lat":"22.423917","long":"114.238553"},{"id":20002248,"name":"利安邨巴士總站","lat":"22.425361","long":"114.240953"}],"routeId":2010270,"description":"特别班次"},{"company":"gmb","route":"803","routeType":2,"orig":"利安","dest":"顯徑","stopList":[{"id":20002248,"name":"利安邨巴士總站","lat":"22.425361","long":"114.240953"},{"id":20002249,"name":"錦英路, 錦龍苑對面","lat":"22.425921","long":"114.239516"},{"id":20002250,"name":"西沙路南行線, 雅典居對面","lat":"22.425516","long":"114.235591"},{"id":20019666,"name":"馬鞍山路近錦駿苑 ","lat":"22.413379","long":"114.226940"},{"id":20001563,"name":"大涌橋路, 濱景花園對面","lat":"22.391642","long":"114.206580"},{"id":20001564,"name":"大涌橋路, 沙田第一城外","lat":"22.388884","long":"114.202554"},{"id":20001553,"name":"大涌橋路, 富豪花園外","lat":"22.384979","long":"114.198441"},{"id":20001554,"name":"大涌橋路,近河畔花園","lat":"22.381818","long":"114.195372"},{"id":20002251,"name":"大涌橋路, 乙明村外","lat":"22.377475","long":"114.191177"},{"id":20002252,"name":"大涌橋路, 曾大屋遊樂場外","lat":"22.375714","long":"114.189439"},{"id":20001571,"name":"車公廟路, 秦石邨外巴士站","lat":"22.374396","long":"114.187264"},{"id":20002253,"name":"車公廟路, 李屋村外","lat":"22.374360","long":"114.184215"},{"id":20001572,"name":"車公廟路, 五育中學外","lat":"22.372247","long":"114.180350"},{"id":20002254,"name":"車公廟路, 田心外","lat":"22.370694","long":"114.177933"},{"id":20002241,"name":"顯田街, 近梁文燕紀念中學","lat":"22.361762","long":"114.174321"}],"routeId":2010270,"description":"特别班次"}]