[{"company":"ctb","route":"955","routeType":null,"dir":"I","orig":"西灣河","dest":"屯門 (菁田及和田)","stopList":[{"id":"001315","name":"港島民生書院, 太安街","lat":"22.283046","long":"114.223300"},{"id":"001367","name":"太富街, 筲箕灣道","lat":"22.283157","long":"114.220949"},{"id":"001288","name":"康怡廣場, 康山道","lat":"22.284500","long":"114.216717"},{"id":"001365","name":"新威園, 英皇道","lat":"22.285529","long":"114.211081"},{"id":"003251","name":"北角官立小學, 英皇道","lat":"22.288852","long":"114.209668"},{"id":"001275","name":"模範邨, 英皇道","lat":"22.291544","long":"114.207667"},{"id":"001276","name":"健康村, 英皇道","lat":"22.291913","long":"114.206341"},{"id":"001033","name":"皇后像廣場, 干諾道中","lat":"22.281992","long":"114.160038"},{"id":"001034","name":"砵典乍街, 干諾道中","lat":"22.283588","long":"114.157304"},{"id":"001628","name":"西區海底隧道巴士轉乘站","lat":"22.305020","long":"114.159204"},{"id":"003359","name":"屯門公路巴士轉乘站(上層), 屯門公路","lat":"22.357549","long":"114.019742"},{"id":"003153","name":"新墟街市, 屯門公路","lat":"22.398931","long":"113.976599"},{"id":"003192","name":"紅橋, 屯門公路","lat":"22.402526","long":"113.977295"},{"id":"003431","name":"虎地, 屯門公路","lat":"22.413265","long":"113.979832"},{"id":"003351","name":"五柳路, 藍地交匯處","lat":"22.415445","long":"113.979676"},{"id":"003209","name":"欣田邨, 青麟路","lat":"22.414753","long":"113.977394"},{"id":"003760","name":"菁田邨","lat":"22.412909","long":"113.972412"},{"id":"003767","name":"NOVO LAND, 欣寶路","lat":"22.411996","long":"113.970350"},{"id":"003752","name":"和田邨","lat":"22.412840","long":"113.968639"}],"routeId":"955","description":"正常班次"},{"company":"ctb","route":"955","routeType":null,"dir":"O","orig":"屯門 (菁田及和田)","dest":"西灣河","stopList":[{"id":"003760","name":"菁田邨","lat":"22.412909","long":"113.972412"},{"id":"003752","name":"和田邨","lat":"22.412840","long":"113.968639"},{"id":"003753","name":"NOVO LAND, 欣寶路","lat":"22.412258","long":"113.970551"},{"id":"003754","name":"紫田村, 欣寶路","lat":"22.414425","long":"113.973893"},{"id":"003207","name":"欣田邨, 青麟路","lat":"22.414225","long":"113.977135"},{"id":"003350","name":"五柳路, 藍地交匯處","lat":"22.415551","long":"113.979758"},{"id":"003656","name":"虎地, 屯門公路","lat":"22.413857","long":"113.980705"},{"id":"003193","name":"紅橋, 屯門公路","lat":"22.402137","long":"113.977501"},{"id":"003358","name":"屯門公路巴士轉乘站, 屯門公路","lat":"22.362538","long":"114.015809"},{"id":"001629","name":"西區海底隧道巴士轉乘站","lat":"22.304234","long":"114.159797"},{"id":"001258","name":"北角消防局, 渣華道","lat":"22.292127","long":"114.207819"},{"id":"001267","name":"北角官立小學, 英皇道","lat":"22.288826","long":"114.209867"},{"id":"001268","name":"新威園, 英皇道","lat":"22.285544","long":"114.211338"},{"id":"001393","name":"船塢里, 英皇道","lat":"22.284774","long":"114.214208"},{"id":"001270","name":"太古城中心, 英皇道","lat":"22.285288","long":"114.217584"},{"id":"001313","name":"太康樓, 太康街","lat":"22.283341","long":"114.221779"},{"id":"001293","name":"鯉景灣, 鯉景道","lat":"22.284069","long":"114.223545"},{"id":"001315","name":"港島民生書院, 太安街","lat":"22.283046","long":"114.223300"}],"routeId":"955","description":"正常班次"}]