[{"company":"ctb","route":"SP10","routeType":null,"dir":"O","orig":"啟德體育園","dest":"中環 (港澳碼頭)","stopList":[{},{"id":"002566","name":"利景酒店, 灣仔道","lat":"22.277832632091","long":"114.17916549053"},{"id":"002537","name":"普樂里, 灣仔道","lat":"22.276798792091","long":"114.17597252053"},{"id":"002445","name":"菲林明道, 軒尼詩道","lat":"22.277602072091","long":"114.17407242053"},{"id":"002446","name":"修頓球場, 軒尼詩道","lat":"22.277433042091","long":"114.17187855053"},{"id":"001141","name":"金鐘 - 高等法院, 金鐘道","lat":"22.278413762091","long":"114.16387262053"},{"id":"001053","name":"滙豐總行大廈, 德輔道中","lat":"22.280739462091","long":"114.15905007053"},{"id":"001056","name":"中環街市, 德輔道中","lat":"22.284855172091","long":"114.15539392053"},{"id":"001027","name":"中環 (港澳碼頭)","lat":"22.288274152091","long":"114.15042248053"}],"routeId":"SP10","description":"正常班次"}]